notion_db_connector/__init__.py
notion_db_connector/api_handler.py
notion_db_connector/client.py
notion_db_connector/exceptions.py
notion_db_connector/local_engine.py
notion_db_connector/models.py
notion_db_connector/query_translator.py
notion_db_connector/sql_parser.py
notion_db_connector-1.0.0.dist-info/METADATA
notion_db_connector-1.0.0.dist-info/WHEEL
notion_db_connector-1.0.0.dist-info/top_level.txt
notion_db_connector-1.0.0.dist-info/RECORD
