Metadata-Version: 2.4
Name: notion-db-connector
Version: 1.0.0
Summary: A powerful Python library to interact with Notion databases using a simple API or raw SQL queries, with support for local caching, offline mode, and advanced SQL features like JOINs.
Author-email: 乔肃 <qiaosu@example.com>
Project-URL: Homepage, https://github.com/example/notion-db-connector
Project-URL: Issues, https://github.com/example/notion-db-connector/issues
Classifier: Programming Language :: Python :: 3
Classifier: License :: OSI Approved :: MIT License
Classifier: Operating System :: OS Independent
Classifier: Development Status :: 5 - Production/Stable
Classifier: Intended Audience :: Developers
Classifier: Topic :: Database
Classifier: Topic :: Office/Business :: Office Suites
Classifier: Framework :: AsyncIO
Requires-Python: >=3.8
Requires-Dist: notion-client
Requires-Dist: python-dotenv
Requires-Dist: sqlglot
Requires-Dist: cachetools>=5.0.0
Requires-Dist: httpx
Requires-Dist: pandas
Provides-Extra: test
Requires-Dist: pytest; extra == "test"
Requires-Dist: pytest-mock; extra == "test"
Requires-Dist: pytest-asyncio; extra == "test"
